lnkcreator/LICENSE
lnkcreator/README.md
lnkcreator/__init__.py
lnkcreator/requirements.txt
lnkcreator/thirdparty.json
lnkcreator-0.10.dist-info/LICENSE.rst
lnkcreator-0.10.dist-info/METADATA
lnkcreator-0.10.dist-info/WHEEL
lnkcreator-0.10.dist-info/top_level.txt
lnkcreator-0.10.dist-info/RECORD
