Metadata-Version: 2.1
Name: lnkcreator
Version: 0.10
Summary: Creates .lnk files on Windows (with Admin rights if desired)
Home-page: https://github.com/hansalemaos/lnkcreator
Author: Johannes Fischer
Author-email: aulasparticularesdealemaosp@gmail.com
License: MIT
Keywords: lnk,shortcut,windows
Classifier: Development Status :: 4 - Beta
Classifier: Programming Language :: Python :: 3 :: Only
Classifier: Programming Language :: Python :: 3.10
Classifier: Topic :: Software Development :: Libraries :: Python Modules
Classifier: Topic :: Utilities
License-File: LICENSE.rst
Requires-Dist: subprocesshidden
